{
    "agent": "DynaOptions_Tab",
    "problem": "GrazingWorld",
    "episodes": 3000,
    "metaParameters": {
        "seed": [0,1,2,3,4,5,6,7,8,9,10,11,12,13,14,15,16,17,18,19,20,21,22,23,24,25,26,27,28,29],
        "exploration_phase": [200],
        "no_reward_exploration": [true],
        "alpha": [0.9,0.7,0.5,0.3,0.1],
        "epsilon": [0.1,0.2,0.3,0.4,0.5],
        "behaviour_alg": ["QLearner"],
        "search_control": ["current"],
        "option_model_alg": ["sutton"],
        "gamma": [1.0],
        "kappa": [0.01,0.001,0.0001],
        "lambda": [0.9],
        "planning_steps": [5],
        "model_planning_steps": [0],
        "reward_sequence_length" : [500]
    }
}
